blobject/__init__.py
blobject-0.0.1a1.dist-info/LICENSE
blobject-0.0.1a1.dist-info/METADATA
blobject-0.0.1a1.dist-info/WHEEL
blobject-0.0.1a1.dist-info/top_level.txt
blobject-0.0.1a1.dist-info/RECORD
